CHANGES.txt
LICENSE.txt
MANIFEST.in
setup.py
Aoss_Tower_a1_Conversion.egg-info/PKG-INFO
Aoss_Tower_a1_Conversion.egg-info/SOURCES.txt
Aoss_Tower_a1_Conversion.egg-info/dependency_links.txt
Aoss_Tower_a1_Conversion.egg-info/requires.txt
Aoss_Tower_a1_Conversion.egg-info/top_level.txt
convertFromASCIIToNETCDF/Util.py
convertFromASCIIToNETCDF/WriteToNetCDF.py
convertFromASCIIToNETCDF/__init__.py
convertFromASCIIToNETCDF/autoRun.py
convertFromASCIIToNETCDF/bundler.py
convertFromASCIIToNETCDF/parser.py
convertFromASCIIToNETCDF/test/ATP.py
convertFromASCIIToNETCDF/test/ATW.py
convertFromASCIIToNETCDF/test/Util.py
convertFromASCIIToNETCDF/test/__init__.py
convertFromASCIIToNETCDF/test/bundler.py
convertFromASCIIToNETCDF/test/testBundler.py
convertFromASCIIToNETCDF/test/testParser.py
convertFromASCIIToNETCDF/test/testUtil.py
convertFromASCIIToNETCDF/test/testWrite.py
docs/README.txt