Metadata-Version: 1.0
Name: Aoss-Tower-a1-Conversion
Version: 1.7.0
Summary: convert AossTower ascii files to netCDF files
Home-page: http://metobs.ssec.wisc.edu
Author: UNKNOWN
Author-email: UNKNOWN
License: UNKNOWN
Platform: UNKNOWN
